{"is_source_file": true, "format": "Dart", "description": "This file defines a JobsProvider class that manages job data, including loading jobs from a database, updating their status, and simulating real-time updates with periodic timer callbacks. It uses Flutter's ChangeNotifier for state management and interacts with a database and Job models.", "external_files": ["../data/database/app_database.dart", "../models/job.dart"], "external_methods": ["AppDatabase.listJobs", "AppDatabase.upsertJob"], "published": ["JobsProvider"], "classes": [{"name": "JobsProvider", "description": "A ChangeNotifier class managing a list of jobs, providing methods to load, update, and simulate real-time status updates for jobs."}], "methods": [{"name": "loadInitial", "description": "Loads initial job data from the database and starts the real-time simulation timer."}, {"name": "updateJobStatus", "description": "Updates the status of a specific job identified by jobId both in local list and database."}, {"name": "_startMockRealtime", "description": "Starts a periodic timer to simulate real-time status changes in jobs."}, {"name": "_next", "description": "Determines the next job status in the simulation sequence."}, {"name": "dispose", "description": "Cancels the timer when the provider is disposed of."}], "calls": ["database.listJobs", "database.upsertJob", "notifyListeners"], "search-terms": ["JobsProvider", "change notifier", "job list management", "mock real-time updates", "job status transition"], "state": 2, "file_id": 31, "knowledge_revision": 76, "git_revision": "", "hash": "9530f4ab87ad21f8c43b8027f231cbfc", "format-version": 4, "code-base-name": "smart_outage_frontend", "filename": "smart_outage_frontend/lib/src/state/jobs_provider.dart", "revision_history": [{"76": ""}]}